db2_mcp_server/__init__.py
db2_mcp_server/cache.py
db2_mcp_server/core.py
db2_mcp_server/logger.py
db2_mcp_server/mcp_instance.py
db2_mcp_server/prompts/__init__.py
db2_mcp_server/prompts/db2_prompts.py
db2_mcp_server/prompts/dynamic_loader.py
db2_mcp_server/resources/__init__.py
db2_mcp_server/resources/db2_resources.py
db2_mcp_server/storage/__init__.py
db2_mcp_server/storage/table_metadata.py
db2_mcp_server/tools/__init__.py
db2_mcp_server/tools/list_tables.py
db2_mcp_server/tools/metadata_retrieval.py
db2_mcp_server-0.2.2.dist-info/licenses/LICENSE
db2_mcp_server-0.2.2.dist-info/METADATA
db2_mcp_server-0.2.2.dist-info/WHEEL
db2_mcp_server-0.2.2.dist-info/entry_points.txt
db2_mcp_server-0.2.2.dist-info/top_level.txt
db2_mcp_server-0.2.2.dist-info/RECORD
