Metadata-Version: 2.4
Name: db2-mcp-server
Version: 0.2.2
Summary: A read-only MCP server for interacting with a DB2 database.
Author-email: Jien Huang <huangjien@gmail.com>
License: MIT License
Project-URL: Homepage, https://github.com/huangjien/db2-mcp-server
Project-URL: Bug Tracker, https://github.com/huangjien/db2-mcp-server/issues
Classifier: Programming Language :: Python :: 3
Classifier: Programming Language :: Python :: 3.12
Classifier: License :: OSI Approved :: MIT License
Classifier: Operating System :: OS Independent
Requires-Python: >=3.12
License-File: LICENSE
Requires-Dist: fastmcp>=2.2.6
Requires-Dist: ibm_db
Requires-Dist: pydantic
Requires-Dist: python-dotenv
Requires-Dist: toml
Requires-Dist: dotenv>=0.9.9
Provides-Extra: dev
Requires-Dist: pytest>=7.0.0; extra == "dev"
Requires-Dist: pytest-cov; extra == "dev"
Requires-Dist: uv<0.7.0,>=0.6.0; extra == "dev"
Dynamic: license-file
